{
  "metadata": {
    "soundFile": "/Users/x.sun/Downloads/Rhubarb-Lip-Sync-1.13.0-macOS/./2_roov_3.ogg",
    "duration": 22.75
  },
  "mouthCues": [
    { "start": 0.00, "end": 0.10, "value": "X" },
    { "start": 0.10, "end": 0.19, "value": "A" },
    { "start": 0.19, "end": 0.28, "value": "C" },
    { "start": 0.28, "end": 0.42, "value": "B" },
    { "start": 0.42, "end": 0.56, "value": "C" },
    { "start": 0.56, "end": 0.89, "value": "B" },
    { "start": 0.89, "end": 0.94, "value": "E" },
    { "start": 0.94, "end": 1.34, "value": "B" },
    { "start": 1.34, "end": 1.48, "value": "C" },
    { "start": 1.48, "end": 1.69, "value": "B" },
    { "start": 1.69, "end": 1.76, "value": "C" },
    { "start": 1.76, "end": 2.60, "value": "B" },
    { "start": 2.60, "end": 2.67, "value": "C" },
    { "start": 2.67, "end": 2.74, "value": "F" },
    { "start": 2.74, "end": 2.81, "value": "B" },
    { "start": 2.81, "end": 2.88, "value": "C" },
    { "start": 2.88, "end": 2.95, "value": "D" },
    { "start": 2.95, "end": 3.31, "value": "B" },
    { "start": 3.31, "end": 3.60, "value": "F" },
    { "start": 3.60, "end": 3.67, "value": "B" },
    { "start": 3.67, "end": 3.81, "value": "C" },
    { "start": 3.81, "end": 3.88, "value": "B" },
    { "start": 3.88, "end": 4.09, "value": "C" },
    { "start": 4.09, "end": 4.44, "value": "B" },
    { "start": 4.44, "end": 4.52, "value": "A" },
    { "start": 4.52, "end": 4.56, "value": "C" },
    { "start": 4.56, "end": 4.60, "value": "B" },
    { "start": 4.60, "end": 4.67, "value": "C" },
    { "start": 4.67, "end": 4.74, "value": "B" },
    { "start": 4.74, "end": 4.82, "value": "A" },
    { "start": 4.82, "end": 4.89, "value": "B" },
    { "start": 4.89, "end": 4.96, "value": "C" },
    { "start": 4.96, "end": 5.03, "value": "B" },
    { "start": 5.03, "end": 5.38, "value": "C" },
    { "start": 5.38, "end": 5.59, "value": "B" },
    { "start": 5.59, "end": 5.66, "value": "C" },
    { "start": 5.66, "end": 5.87, "value": "B" },
    { "start": 5.87, "end": 6.12, "value": "C" },
    { "start": 6.12, "end": 6.17, "value": "B" },
    { "start": 6.17, "end": 6.37, "value": "C" },
    { "start": 6.37, "end": 6.39, "value": "A" },
    { "start": 6.39, "end": 6.47, "value": "B" },
    { "start": 6.47, "end": 6.54, "value": "A" },
    { "start": 6.54, "end": 6.80, "value": "B" },
    { "start": 6.80, "end": 6.87, "value": "A" },
    { "start": 6.87, "end": 6.93, "value": "F" },
    { "start": 6.93, "end": 7.01, "value": "A" },
    { "start": 7.01, "end": 7.19, "value": "C" },
    { "start": 7.19, "end": 7.82, "value": "B" },
    { "start": 7.82, "end": 7.96, "value": "C" },
    { "start": 7.96, "end": 8.10, "value": "B" },
    { "start": 8.10, "end": 8.17, "value": "C" },
    { "start": 8.17, "end": 8.66, "value": "B" },
    { "start": 8.66, "end": 8.87, "value": "E" },
    { "start": 8.87, "end": 9.08, "value": "B" },
    { "start": 9.08, "end": 9.15, "value": "E" },
    { "start": 9.15, "end": 9.44, "value": "B" },
    { "start": 9.44, "end": 9.64, "value": "C" },
    { "start": 9.64, "end": 9.71, "value": "B" },
    { "start": 9.71, "end": 9.78, "value": "C" },
    { "start": 9.78, "end": 10.06, "value": "E" },
    { "start": 10.06, "end": 10.19, "value": "A" },
    { "start": 10.19, "end": 10.24, "value": "B" },
    { "start": 10.24, "end": 10.29, "value": "C" },
    { "start": 10.29, "end": 10.50, "value": "B" },
    { "start": 10.50, "end": 10.57, "value": "F" },
    { "start": 10.57, "end": 10.65, "value": "A" },
    { "start": 10.65, "end": 10.70, "value": "C" },
    { "start": 10.70, "end": 10.81, "value": "B" },
    { "start": 10.81, "end": 10.95, "value": "C" },
    { "start": 10.95, "end": 11.02, "value": "E" },
    { "start": 11.02, "end": 11.25, "value": "B" },
    { "start": 11.25, "end": 11.57, "value": "C" },
    { "start": 11.57, "end": 11.64, "value": "B" },
    { "start": 11.64, "end": 11.71, "value": "H" },
    { "start": 11.71, "end": 11.78, "value": "C" },
    { "start": 11.78, "end": 11.85, "value": "B" },
    { "start": 11.85, "end": 12.06, "value": "C" },
    { "start": 12.06, "end": 12.14, "value": "A" },
    { "start": 12.14, "end": 12.23, "value": "B" },
    { "start": 12.23, "end": 12.30, "value": "C" },
    { "start": 12.30, "end": 12.51, "value": "D" },
    { "start": 12.51, "end": 12.65, "value": "C" },
    { "start": 12.65, "end": 12.93, "value": "B" },
    { "start": 12.93, "end": 13.21, "value": "F" },
    { "start": 13.21, "end": 13.29, "value": "A" },
    { "start": 13.29, "end": 13.37, "value": "H" },
    { "start": 13.37, "end": 13.51, "value": "C" },
    { "start": 13.51, "end": 13.72, "value": "B" },
    { "start": 13.72, "end": 13.86, "value": "F" },
    { "start": 13.86, "end": 13.93, "value": "C" },
    { "start": 13.93, "end": 14.42, "value": "B" },
    { "start": 14.42, "end": 14.66, "value": "C" },
    { "start": 14.66, "end": 14.75, "value": "A" },
    { "start": 14.75, "end": 14.81, "value": "B" },
    { "start": 14.81, "end": 15.08, "value": "C" },
    { "start": 15.08, "end": 15.22, "value": "E" },
    { "start": 15.22, "end": 15.29, "value": "F" },
    { "start": 15.29, "end": 15.48, "value": "D" },
    { "start": 15.48, "end": 15.53, "value": "C" },
    { "start": 15.53, "end": 15.71, "value": "B" },
    { "start": 15.71, "end": 15.85, "value": "C" },
    { "start": 15.85, "end": 15.93, "value": "A" },
    { "start": 15.93, "end": 16.02, "value": "D" },
    { "start": 16.02, "end": 16.23, "value": "B" },
    { "start": 16.23, "end": 16.31, "value": "A" },
    { "start": 16.31, "end": 16.74, "value": "B" },
    { "start": 16.74, "end": 16.81, "value": "E" },
    { "start": 16.81, "end": 17.16, "value": "C" },
    { "start": 17.16, "end": 17.24, "value": "A" },
    { "start": 17.24, "end": 17.34, "value": "C" },
    { "start": 17.34, "end": 17.55, "value": "B" },
    { "start": 17.55, "end": 17.69, "value": "C" },
    { "start": 17.69, "end": 17.97, "value": "B" },
    { "start": 17.97, "end": 18.11, "value": "C" },
    { "start": 18.11, "end": 18.67, "value": "B" },
    { "start": 18.67, "end": 18.81, "value": "F" },
    { "start": 18.81, "end": 18.88, "value": "E" },
    { "start": 18.88, "end": 19.02, "value": "H" },
    { "start": 19.02, "end": 19.09, "value": "C" },
    { "start": 19.09, "end": 19.37, "value": "B" },
    { "start": 19.37, "end": 19.44, "value": "F" },
    { "start": 19.44, "end": 19.51, "value": "B" },
    { "start": 19.51, "end": 19.58, "value": "C" },
    { "start": 19.58, "end": 19.72, "value": "B" },
    { "start": 19.72, "end": 19.79, "value": "C" },
    { "start": 19.79, "end": 19.86, "value": "B" },
    { "start": 19.86, "end": 20.14, "value": "C" },
    { "start": 20.14, "end": 20.21, "value": "B" },
    { "start": 20.21, "end": 20.29, "value": "A" },
    { "start": 20.29, "end": 20.40, "value": "B" },
    { "start": 20.40, "end": 20.47, "value": "C" },
    { "start": 20.47, "end": 20.55, "value": "A" },
    { "start": 20.55, "end": 21.22, "value": "B" },
    { "start": 21.22, "end": 21.29, "value": "C" },
    { "start": 21.29, "end": 21.37, "value": "A" },
    { "start": 21.37, "end": 21.49, "value": "C" },
    { "start": 21.49, "end": 22.12, "value": "B" },
    { "start": 22.12, "end": 22.26, "value": "C" },
    { "start": 22.26, "end": 22.54, "value": "B" },
    { "start": 22.54, "end": 22.75, "value": "X" }
  ]
}
